pyfreedompro/__init__.py
pyfreedompro/functions.py
pyfreedompro-1.1.0.dist-info/LICENSE
pyfreedompro-1.1.0.dist-info/METADATA
pyfreedompro-1.1.0.dist-info/WHEEL
pyfreedompro-1.1.0.dist-info/top_level.txt
pyfreedompro-1.1.0.dist-info/RECORD
