Metadata-Version: 2.1
Name: pyfreedompro
Version: 1.1.0
Summary: Freedompro API
Home-page: https://github.com/stefano055415/pyfreedompro
Author: Stefano Cartisano
Author-email: stefano055415@gmail.com
License: UNKNOWN
Project-URL: Bug Tracker, https://github.com/stefano055415/pyfreedompro/issues
Platform: UNKNOWN
Classifier: Programming Language :: Python :: 3
Classifier: License :: OSI Approved :: MIT License
Classifier: Operating System :: OS Independent
Requires-Python: >=3.6
